nutrient_sdk_native/__init__.py
nutrient_sdk_native/lib/linux-arm64/NativeSDK.Imaging.ML.arm64.so
nutrient_sdk_native/lib/linux-arm64/NativeSDK.Imaging.Rendering.Skia.arm64.so
nutrient_sdk_native/lib/linux-arm64/NativeSDK.barcode.1d.reader.arm64.so
nutrient_sdk_native/lib/linux-arm64/NativeSDK.barcode.2d.reader.arm64.so
nutrient_sdk_native/lib/linux-arm64/NativeSDK.filters.arm64.so
nutrient_sdk_native/lib/linux-arm64/NativeSDK.image.gdimgplug.arm64.so
nutrient_sdk_native/lib/linux-arm64/NativeSDK.machine.vision.arm64.so
nutrient_sdk_native/lib/linux-arm64/NativeSDK.so
nutrient_sdk_native/lib/linux-arm64/libNativeSDK.so
nutrient_sdk_native-1.0.1.dist-info/METADATA
nutrient_sdk_native-1.0.1.dist-info/WHEEL
nutrient_sdk_native-1.0.1.dist-info/top_level.txt
nutrient_sdk_native-1.0.1.dist-info/RECORD
