Metadata-Version: 2.4
Name: nutrient-sdk-native
Version: 1.0.1
Summary: Nutrient SDK native libraries
Author-email: Nutrient <support@nutrient.io>
License: Proprietary
Keywords: nutrient,native
Classifier: Development Status :: 5 - Production/Stable
Classifier: Intended Audience :: Developers
Classifier: Programming Language :: Python :: 3
Requires-Python: >=3.8
